LICENSE
README.md
setup.py
cytopus/__init__.py
cytopus.egg-info/PKG-INFO
cytopus.egg-info/SOURCES.txt
cytopus.egg-info/dependency_links.txt
cytopus.egg-info/requires.txt
cytopus.egg-info/top_level.txt
cytopus/data/Cytopus_1.2.txt
cytopus/data/Cytopus_1.22.txt
cytopus/data/Cytopus_1.23.txt
cytopus/data/Cytopus_1.31nc.txt
cytopus/knowledge_base/__init__.py
cytopus/knowledge_base/kb_queries.py
cytopus/tools/__init__.py
cytopus/tools/create.py
cytopus/tools/label.py
tests/test_initialise_cytopus.py