Metadata-Version: 2.1
Name: cytopus
Version: 1.3.4
Author: Thomas Walle
License-File: LICENSE
Requires-Dist: numpy>1.2
Requires-Dist: networkx>2.7
